{
    "id": 0,
    "slug": "",
    "title": "Cinnamon Rolls",
    "thumbnail": "",
    "temp_fahrenheit": 0,
    "temp_celsius": 0,
    "video_url": "https://www.youtube.com/embed/nxXefoJvxoI",
    "created_at": "",
    "components": [
        {
            "id": 0,
            "name": "Main Ingredients",
            "ingredients": [
                {
                    "name": "Milk",
                    "quantity": 1,
                    "unit": "cup",
                    "metric_quantity": 0,
                    "metric_unit": "",
                    "optional": false,
                    "notes": [
                        ""
                    ]
                },
                {
                    "name": "Butter",
                    "quantity": 3,
                    "unit": "cubes",
                    "metric_quantity": 0,
                    "metric_unit": "",
                    "optional": false,
                    "notes": [
                        "each cube is half a cup"
                    ]
                },
                {
                    "name": "Instant Yeast",
                    "quantity": 2,
                    "unit": "tbsp",
                    "metric_quantity": 0,
                    "metric_unit": "",
                    "optional": false,
                    "notes": [
                        ""
                    ]
                },
                {
                    "name": "Sugar",
                    "quantity": 2,
                    "unit": "cups",
                    "metric_quantity": 0,
                    "metric_unit": "",
                    "optional": false,
                    "notes": [
                        "plus 1 tbsp"
                    ]
                },
                {
                    "name": "Water",
                    "quantity": 1,
                    "unit": "cup",
                    "metric_quantity": 0,
                    "metric_unit": "",
                    "optional": false,
                    "notes": [
                        ""
                    ]
                },
                {
                    "name": "Eggs",
                    "quantity": 3,
                    "unit": "",
                    "metric_quantity": 0,
                    "metric_unit": "",
                    "optional": false,
                    "notes": [
                        ""
                    ]
                },
                {
                    "name": "Flour",
                    "quantity": 7,
                    "unit": "cups",
                    "metric_quantity": 0,
                    "metric_unit": "",
                    "optional": false,
                    "notes": [
                        "6-7 cups depending on humidity"
                    ]
                },
                {
                    "name": "Salt",
                    "quantity": 1,
                    "unit": "tsp",
                    "metric_quantity": 0,
                    "metric_unit": "",
                    "optional": false,
                    "notes": [
                        ""
                    ]
                },
                {
                    "name": "Ground Cinnamon",
                    "quantity": 2,
                    "unit": "tbsp",
                    "metric_quantity": 0,
                    "metric_unit": "",
                    "optional": false,
                    "notes": [
                        ""
                    ]
                },
                {
                    "name": "Powdered Sugar",
                    "quantity": 1,
                    "unit": "package",
                    "metric_quantity": 0,
                    "metric_unit": "",
                    "optional": false,
                    "notes": [
                        ""
                    ]
                },
                {
                    "name": "Vanilla Extract",
                    "quantity": 1,
                    "unit": "tsp",
                    "metric_quantity": 0,
                    "metric_unit": "",
                    "optional": false,
                    "notes": [
                        ""
                    ]
                }
            ]
        }
    ],
    "tools": [],
    "notes": [
        ""
    ],
    "tags": [
        "cinnamon-rolls",
        "yeast-dough",
        "sweet-bread",
        "baked-goods",
        "homemade",
        "comfort-food"
    ]
}